<?xml version="1.0" encoding="UTF-8"?>
<!DOCTYPE mapper PUBLIC "-//mybatis.org//DTD Mapper 3.0//EN" "http://mybatis.org/dtd/mybatis-3-mapper.dtd">
<mapper namespace="com.example.dao.BlogMapper">
  <resultMap id="BaseResultMap" type="com.example.entity.Blog">
    <!--
      WARNING - @mbg.generated
      This element is automatically generated by MyBatis Generator, do not modify.
      This element was generated on Thu Apr 21 13:52:39 CST 2022.
    -->
    <constructor>
      <idArg column="id" javaType="java.lang.String" jdbcType="VARCHAR" />
      <arg column="title" javaType="java.lang.String" jdbcType="VARCHAR" />
      <arg column="create_date_time" javaType="java.util.Date" jdbcType="TIMESTAMP" />
      <arg column="modify_date_time" javaType="java.util.Date" jdbcType="TIMESTAMP" />
    </constructor>
  </resultMap>
  <resultMap id="ResultMapWithBLOBs" type="com.example.entity.Blog">
    <!--
      WARNING - @mbg.generated
      This element is automatically generated by MyBatis Generator, do not modify.
      This element was generated on Thu Apr 21 13:52:39 CST 2022.
    -->
    <constructor>
      <idArg column="id" javaType="java.lang.String" jdbcType="VARCHAR" />
      <arg column="title" javaType="java.lang.String" jdbcType="VARCHAR" />
      <arg column="create_date_time" javaType="java.util.Date" jdbcType="TIMESTAMP" />
      <arg column="modify_date_time" javaType="java.util.Date" jdbcType="TIMESTAMP" />
      <arg column="content" javaType="java.lang.String" jdbcType="LONGVARCHAR" />
    </constructor>
  </resultMap>
  <sql id="Base_Column_List">
    <!--
      WARNING - @mbg.generated
      This element is automatically generated by MyBatis Generator, do not modify.
      This element was generated on Thu Apr 21 13:52:39 CST 2022.
    -->
    id, title, create_date_time, modify_date_time
  </sql>
  <sql id="Blob_Column_List">
    <!--
      WARNING - @mbg.generated
      This element is automatically generated by MyBatis Generator, do not modify.
      This element was generated on Thu Apr 21 13:52:39 CST 2022.
    -->
    content
  </sql>
  <select id="selectByPrimaryKey" parameterType="java.lang.String" resultMap="ResultMapWithBLOBs">
    <!--
      WARNING - @mbg.generated
      This element is automatically generated by MyBatis Generator, do not modify.
      This element was generated on Thu Apr 21 13:52:39 CST 2022.
    -->
    select 
    <include refid="Base_Column_List" />
    ,
    <include refid="Blob_Column_List" />
    from blog
    where id = #{id,jdbcType=VARCHAR}
  </select>
  <delete id="deleteByPrimaryKey" parameterType="java.lang.String">
    <!--
      WARNING - @mbg.generated
      This element is automatically generated by MyBatis Generator, do not modify.
      This element was generated on Thu Apr 21 13:52:39 CST 2022.
    -->
    delete from blog
    where id = #{id,jdbcType=VARCHAR}
  </delete>
  <insert id="insert" parameterType="com.example.entity.Blog">
    <!--
      WARNING - @mbg.generated
      This element is automatically generated by MyBatis Generator, do not modify.
      This element was generated on Thu Apr 21 13:52:39 CST 2022.
    -->
    insert into blog (id, title, create_date_time, 
      modify_date_time, content)
    values (#{id,jdbcType=VARCHAR}, #{title,jdbcType=VARCHAR}, #{createDateTime,jdbcType=TIMESTAMP}, 
      #{modifyDateTime,jdbcType=TIMESTAMP}, #{content,jdbcType=LONGVARCHAR})
  </insert>
  <insert id="insertSelective" parameterType="com.example.entity.Blog">
    <!--
      WARNING - @mbg.generated
      This element is automatically generated by MyBatis Generator, do not modify.
      This element was generated on Thu Apr 21 13:52:39 CST 2022.
    -->
    insert into blog
    <trim prefix="(" suffix=")" suffixOverrides=",">
      <if test="id != null">
        id,
      </if>
      <if test="title != null">
        title,
      </if>
      <if test="createDateTime != null">
        create_date_time,
      </if>
      <if test="modifyDateTime != null">
        modify_date_time,
      </if>
      <if test="content != null">
        content,
      </if>
    </trim>
    <trim prefix="values (" suffix=")" suffixOverrides=",">
      <if test="id != null">
        #{id,jdbcType=VARCHAR},
      </if>
      <if test="title != null">
        #{title,jdbcType=VARCHAR},
      </if>
      <if test="createDateTime != null">
        #{createDateTime,jdbcType=TIMESTAMP},
      </if>
      <if test="modifyDateTime != null">
        #{modifyDateTime,jdbcType=TIMESTAMP},
      </if>
      <if test="content != null">
        #{content,jdbcType=LONGVARCHAR},
      </if>
    </trim>
  </insert>
  <update id="updateByPrimaryKeySelective" parameterType="com.example.entity.Blog">
    <!--
      WARNING - @mbg.generated
      This element is automatically generated by MyBatis Generator, do not modify.
      This element was generated on Thu Apr 21 13:52:39 CST 2022.
    -->
    update blog
    <set>
      <if test="title != null">
        title = #{title,jdbcType=VARCHAR},
      </if>
      <if test="createDateTime != null">
        create_date_time = #{createDateTime,jdbcType=TIMESTAMP},
      </if>
      <if test="modifyDateTime != null">
        modify_date_time = #{modifyDateTime,jdbcType=TIMESTAMP},
      </if>
      <if test="content != null">
        content = #{content,jdbcType=LONGVARCHAR},
      </if>
    </set>
    where id = #{id,jdbcType=VARCHAR}
  </update>
  <update id="updateByPrimaryKeyWithBLOBs" parameterType="com.example.entity.Blog">
    <!--
      WARNING - @mbg.generated
      This element is automatically generated by MyBatis Generator, do not modify.
      This element was generated on Thu Apr 21 13:52:39 CST 2022.
    -->
    update blog
    set title = #{title,jdbcType=VARCHAR},
      create_date_time = #{createDateTime,jdbcType=TIMESTAMP},
      modify_date_time = #{modifyDateTime,jdbcType=TIMESTAMP},
      content = #{content,jdbcType=LONGVARCHAR}
    where id = #{id,jdbcType=VARCHAR}
  </update>
  <update id="updateByPrimaryKey" parameterType="com.example.entity.Blog">
    <!--
      WARNING - @mbg.generated
      This element is automatically generated by MyBatis Generator, do not modify.
      This element was generated on Thu Apr 21 13:52:39 CST 2022.
    -->
    update blog
    set title = #{title,jdbcType=VARCHAR},
      create_date_time = #{createDateTime,jdbcType=TIMESTAMP},
      modify_date_time = #{modifyDateTime,jdbcType=TIMESTAMP}
    where id = #{id,jdbcType=VARCHAR}
  </update>
</mapper>